House_price_prediction/__init__.py
House_price_prediction/ingest_data.py
House_price_prediction/score.py
House_price_prediction/train.py
House_price_prediction_6110-0.2.dist-info/METADATA
House_price_prediction_6110-0.2.dist-info/WHEEL
House_price_prediction_6110-0.2.dist-info/top_level.txt
House_price_prediction_6110-0.2.dist-info/RECORD
